sign_in_app.py
sign_in_app-0.0.3.dist-info/LICENSE
sign_in_app-0.0.3.dist-info/METADATA
sign_in_app-0.0.3.dist-info/WHEEL
sign_in_app-0.0.3.dist-info/entry_points.txt
sign_in_app-0.0.3.dist-info/top_level.txt
sign_in_app-0.0.3.dist-info/RECORD
