Metadata-Version: 2.1
Name: sign-in-app
Version: 0.0.3
Summary: A small example package
Author-email: Scott Gruenewald <s.gruenewald.work@gmail.com>
License: MIT License        
Project-URL: Homepage, https://pypi.org/manage/project/sign-in-app
Project-URL: Bug Tracker, https://github.com/scottgruenewald/sign_in_app_old/issues
Keywords: sign,in
Classifier: Programming Language :: Python :: 3
Classifier: License :: OSI Approved :: MIT License
Classifier: Operating System :: OS Independent
Requires-Python: >=3.0
License-File: LICENSE
Requires-Dist: requests
Requires-Dist: python-dateutil
